{
    "prepare_queue": {
        "installed": [],
        "uninstalled": []
    },
    "config_munge": {
        "files": {}
    },
    "installed_plugins": {
        "cordova-plugin-whitelist": {
            "PACKAGE_NAME": "View"
        },
        "cordova-plugin-datepicker": {
            "PACKAGE_NAME": "ch.heg.perfview"
        },
        "cordova-plugin-geolocation": {
            "PACKAGE_NAME": "ch.heg.perfview"
        },
        "cordova-plugin-camera": {
            "PACKAGE_NAME": "ch.heg.perfview"
        },
        "cordova-sqlite-plugin": {
            "PACKAGE_NAME": "ch.heg.perfview"
        },
        "cordova-plugin-calendar": {
            "PACKAGE_NAME": "ch.heg.perfview"
        },
        "cordova-plugin-device-orientation": {
            "PACKAGE_NAME": "ch.heg.perfview"
        },
        "cordova-plugin-nativeaudio": {
            "PACKAGE_NAME": "ch.heg.perfview"
        },
        "cordova-plugin-contacts": {
            "PACKAGE_NAME": "ch.heg.perfview"
        },
        "cordova-plugin-device-motion": {
            "PACKAGE_NAME": "ch.heg.perfview"
        },
        "cordova-plugin-x-socialsharing": {
            "PACKAGE_NAME": "ch.heg.perfview"
        }
    },
    "dependent_plugins": {
        "cordova-plugin-compat": {
            "PACKAGE_NAME": "ch.heg.perfview"
        },
        "es6-promise-plugin": {
            "PACKAGE_NAME": "ch.heg.perfview"
        }
    }
}